pycloud189/__init__.py
pycloud189/api/__init__.py
pycloud189/api/cloudpan189.py
pycloud189/cmds/__init__.py
pycloud189/cmds/cmdbase.py
pycloud189/conf/__init__.py
pycloud189/conf/const.py
pycloud189/log/__init__.py
pycloud189/log/logger.py
tests/__init__.py
pycloud189-0.0.4.dist-info/LICENSE
pycloud189-0.0.4.dist-info/METADATA
pycloud189-0.0.4.dist-info/WHEEL
pycloud189-0.0.4.dist-info/top_level.txt
pycloud189-0.0.4.dist-info/RECORD
